<?xml version="1.0" encoding="utf-8"?>
<Patch>

	<Operation Class="PatchOperationReplace">
		<xpath>/Defs/InteractionDef[defName = "RomanceAttempt"]/logRulesInitiator/rulesStrings</xpath>
		<value>
		  <rulesStrings>
			<li>r_logentry->[attempt]</li>
				<li>attempt(INITIATOR_relationship==Lover,tag=RomanceSuccess)->[try_romance]</li>
				<li>attempt(priority=-1,tag=RomanceFail)->[try_romance]</li>

				<li>try_romance->Oh, lily-perfumed lips! You are my only Spring!</li>
				<li>try_romance->Your eyes shine like stars — stars whose pointy ends pierce my heart...</li>
				<li>try_romance->To me, [RECIPIENT_nameDef], you're as [beautiful] as a [romantic_adj] [romantic_noun]...</li>
				<li>try_romance->I wish I were your mirror, so that I could admire you all day long...</li>
				<li>try_romance->You're the best thing I could hope to happen in my life...</li>
				<li>try_romance->Although it won't last, this blissful moment I spent with you will be forever in my dreams...</li>
				
				<li>try_romance(RECIPIENT_trait==annoying voice)->Of all terrible sounds in the world, your voice is my favorite.</li>
				<li>try_romance(RECIPIENT_trait==bodypurist)->No wonder you abhor body modifications — because yours is perfect already!</li>
				<li>try_romance(RECIPIENT_trait==bodymodder)->Wanna help me pick a heart upgrade? 'Cause mine just skipped a beat for you!</li>
				<li>try_romance(RECIPIENT_trait==gourmand)->If I could, I'd turn into a plate of delicacies, just to please your senses...</li>
		
				<li>try_romance(RECIPIENT_trait==night owl)->When I spot you walking in the dead of night, you shine in my heart as a bright angel of light...</li>
				
				
				<li>try_romance(RECIPIENT_trait==nervous)->[nervotile]</li>
				<li>try_romance(RECIPIENT_trait==volatile)->[nervotile]</li>
					<li>nervotile->Please don't freak out, but I like you very much. Do you like me back? Don't worry, you have time to think about it.</li>
				
				<li>try_romance(RECIPIENT_trait==beautiful)->[beautty]</li>
				<li>try_romance(RECIPIENT_trait==pretty)->[beautty]</li>
					<li>beautty->Honey, sugar and cinnamon — here's what your mother used to make you, I'm sure!</li>
					<li>beautty->Roses are red, violets are blue, and sugar is sweet — But not nearly as sweet as you!</li>
					<li>beautty->You walk in beauty like the night, with all that's best of dark and bright...</li>
					<li>beautty->The most beautiful among the beautiful will still never be as beautiful as you!</li>
					<li>beautty->Your perfumed skin puts into my heart a thousand [romantic_adj] late-night thoughts...</li>
					<li>beautty(INITIATOR_trait==abrasive)->Your perfumed skin puts into my heart a thousand naughty thoughts...</li>
					
				<li>try_romance(RECIPIENT_trait==bloodlust)->[bloodbrawl]</li>
				<li>try_romance(RECIPIENT_trait==brawler)->[bloodbrawl]</li>
					<li>bloodbrawl->Strong as a bear, fierce as a warg... you're just a dream come true!</li>
					
				<li>try_romance(RECIPIENT_trait==kind)->Your soothing kindness is a healing balm for my soul...</li>
				
				<li>try_romance(RECIPIENT_trait==abrasive)->Your strong personality turns me on just like fire sparks on an oil patch!</li>
				
				<li>try_romance(RECIPIENT_trait==too smart)->Will your vast ocean of knowledge ever hold the love I feel for you?</li>
				
				<li>try_romance(RECIPIENT_trait==nimble)->Your smooth and elegant movements hypnotize my eyes and sway my heart...</li>
				
				<li>try_romance(RECIPIENT_trait==staggeringly ugly)->[uglyLove]</li>
				<li>try_romance(RECIPIENT_trait==ugly)->[uglyLove]</li>
				<li>uglyLove->Love looks not with the eyes, but with the mind — And therefore is winged Cupid painted blind... I treasure you, darling [RECIPIENT_nameDef]!</li>
				
				<li>try_romance(INITIATOR_TRAIT==nimble)->[fastMoving]</li>
				<li>try_romance(INITIATOR_TRAIT==jogger)->[fastMoving]</li>
				<li>try_romance(INITIATOR_TRAIT==fast walker)->[fastMoving]</li>
				<li>fastMoving->You make my heart race faster than my feet, [beautiful] [RECIPIENT_nameDef]!</li>
				
				<li>try_romance(INITIATOR_TRAIT==chemical fascination)->[chemical]</li>
				<li>try_romance(INITIATOR_TRAIT==chemical interest)->[chemical]</li>
				<li>chemical(INITIATOR_intellectual_level>=5)->I find your presence simply intoxicating, [RECIPIENT_nameDef].</li>
				<li>chemical->When I'm around you, [RECIPIENT_nameDef], I feel a strong buzz — I think I'm tripping on love...</li>
				
				<li>try_romance(INITIATOR_TRAIT==industrious)->[industriousWorking]</li>
				<li>try_romance(INITIATOR_TRAIT==hard worker)->[industriousWorking]</li>
				<li>industriousWorking->For your love, [RECIPIENT_nameDef], I'll do anything — just say the word.</li>
				
				<li>try_romance(INITIATOR_TRAIT==lazy)->[lazySlothful]</li>
				<li>try_romance(INITIATOR_TRAIT==slothful)->[lazySlothful]</li>
				<li>lazySlothful->I've never focused on anything the way I focus on you, [RECIPIENT_nameDef].</li>
				<li>lazySlothful->I know I'm not known for trying hard, [RECIPIENT_nameDef], but to make you smile, I would put in the effort.</li>
				
				<li>try_romance(INITIATOR_TRAIT==abrasive)->Hey, [RECIPIENT_nameDef], baby — you want some of this? *wink*</li>
				<li>try_romance(INITIATOR_TRAIT==bloodlust)->I would fight a thousand and one battles to win your loving smile, [RECIPIENT_nameDef].</li>
				<li>try_romance(INITIATOR_TRAIT==psychopath)->... [RECIPIENT_nameDef]. You're [beautiful]. Be mine.</li>
				<li>try_romance(INITIATOR_TRAIT==gourmand)->You're more delicious than anything I've seen on a plate, [RECIPIENT_nameDef].</li>
					
			<li>beautiful->beautiful</li>
			<li>beautiful->charming</li>
			<li>beautiful->gorgeous</li>
			<li>beautiful->lovely</li>

			<li>romantic_adj->shining</li>
			<li>romantic_adj->glimmering</li>
			<li>romantic_adj->heavenly</li>
			<li>romantic_adj->golden</li>
			<li>romantic_adj->bright</li>
			<li>romantic_adj->breathtaking</li>
			<li>romantic_adj->dazzling</li>
			<li>romantic_adj->delicate</li>
			<li>romantic_adj->fine</li>
			<li>romantic_adj->magnificent</li>
			<li>romantic_adj->wonderful</li>

			<li>romantic_noun->flower</li>
			<li>romantic_noun->spring</li>
			<li>romantic_noun->river</li>
			<li>romantic_noun->star</li>
			<li>romantic_noun->moon</li>
			<li>romantic_noun->sun</li>
			<li>romantic_noun->sunrise</li>
			<li>romantic_noun->house</li>
			<li>romantic_noun->aurora</li>
			<li>romantic_noun->[TreeType] tree</li>
			<li>romantic_noun(p=2)->[TerrainFeature]</li>

		  </rulesStrings>
		</value>
	</Operation>

	<Operation Class="PatchOperationReplace">
		<xpath>/Defs/InteractionDef[defName = "MarriageProposal"]/logRulesInitiator/rulesStrings</xpath>
		<value>
		  <rulesStrings>
			<li>r_logentry->[attempt]</li>
				<li>attempt(priority=1,INITIATOR_relationship==Spouse,tag=ProposalSuccess)->[propose]</li>
				<li>attempt(INITIATOR_relationship!=Fiance,tag=ProposalBreakup)->[propose]</li>
				<li>attempt(priority=-1,tag=ProposalFail)->[propose]</li>

				<li>propose->[RECIPIENT_nameFull], will you marry me?</li>

		  </rulesStrings>
		</value>
	</Operation>
	
	<Operation Class="PatchOperationReplace">
		<xpath>/Defs/InteractionDef[defName = "Breakup"]/logRulesInitiator/rulesStrings</xpath>
		<value>
			 <rulesStrings>
				<li>r_logentry->[RECIPIENT_nameDef], I'm sorry... I need some space... I think we should break up...</li>
				<li>r_logentry->[RECIPIENT_nameDef], it looks like our relationship isn't working out... We should see other people...</li>
				<li>r_logentry->[RECIPIENT_nameDef], I don't think it's working between us... It's not you, it's me.</li>
			  </rulesStrings>
		</value>
	</Operation>

</Patch>
